uw_restclients_graderoster-1.1.6.dist-info/licenses/LICENSE
uw_sws_graderoster/VERSION
uw_sws_graderoster/__init__.py
uw_sws_graderoster/dao.py
uw_sws_graderoster/models.py
uw_sws_graderoster/test.py
uw_sws_graderoster/resources/sws/file/student/v5/graderoster/2013_autumn_EDC_I_461_A_FBB38FE46A7C11D5A4AE0004AC494FFE
uw_sws_graderoster/resources/sws/file/student/v5/graderoster/2013_summer_CSS_161_A_FBB38FE46A7C11D5A4AE0004AC494FFE
uw_sws_graderoster/templates/graderoster.xhtml
uw_sws_graderoster/tests/__init__.py
uw_sws_graderoster/tests/test_dao.py
uw_sws_graderoster/tests/test_graderoster.py
uw_sws_graderoster/tests/test_gradingscale.py
uw_restclients_graderoster-1.1.6.dist-info/METADATA
uw_restclients_graderoster-1.1.6.dist-info/WHEEL
uw_restclients_graderoster-1.1.6.dist-info/top_level.txt
uw_restclients_graderoster-1.1.6.dist-info/RECORD
