Metadata-Version: 2.4
Name: UW-RestClients-Graderoster
Version: 1.1.6
Summary: A library for connecting to the SWS Graderoster API at the University of Washington.
Home-page: https://github.com/uw-it-aca/uw-restclients-graderoster
Author: UW-IT T&LS
Author-email: aca-it@uw.edu
License: Apache License, Version 2.0
Classifier: Intended Audience :: Developers
Classifier: License :: OSI Approved :: Apache Software License
Classifier: Operating System :: OS Independent
Classifier: Programming Language :: Python
License-File: LICENSE
Requires-Dist: uw-restclients-core~=1.4
Requires-Dist: uw-restclients-sws~=2.4
Requires-Dist: uw-restclients-pws~=2.1
Requires-Dist: mock
Requires-Dist: lxml
Requires-Dist: jinja2
Dynamic: author
Dynamic: author-email
Dynamic: classifier
Dynamic: description
Dynamic: home-page
Dynamic: license
Dynamic: license-file
Dynamic: requires-dist
Dynamic: summary
